{
  "transcript": "Useless Information. I read in a book that, giraffes, have no voices. The Red Sea, is blue. Gorillas, can't swim. Black treacle, is brown. Elephants, can't jump. And nothing, rhymes with orange. Does it?",
  "words": [
    {
      "alignedWord": "useless",
      "case": "success",
      "end": 1.4,
      "endOffset": 7,
      "phones": [
        {
          "duration": 0.11,
          "phone": "y_B"
        },
        {
          "duration": 0.11,
          "phone": "uw_I"
        },
        {
          "duration": 0.11,
          "phone": "s_I"
        },
        {
          "duration": 0.08,
          "phone": "l_I"
        },
        {
          "duration": 0.06,
          "phone": "ah_I"
        },
        {
          "duration": 0.16,
          "phone": "s_E"
        }
      ],
      "start": 0.77,
      "startOffset": 0,
      "word": "Useless"
    },
    {
      "alignedWord": "information",
      "case": "success",
      "end": 2.34,
      "endOffset": 19,
      "phones": [
        {
          "duration": 0.15,
          "phone": "ih_B"
        },
        {
          "duration": 0.09,
          "phone": "n_I"
        },
        {
          "duration": 0.08,
          "phone": "f_I"
        },
        {
          "duration": 0.06,
          "phone": "er_I"
        },
        {
          "duration": 0.08,
          "phone": "m_I"
        },
        {
          "duration": 0.12,
          "phone": "ey_I"
        },
        {
          "duration": 0.13,
          "phone": "sh_I"
        },
        {
          "duration": 0.06,
          "phone": "ah_I"
        },
        {
          "duration": 0.15,
          "phone": "n_E"
        }
      ],
      "start": 1.42,
      "startOffset": 8,
      "word": "Information"
    },
    {
      "alignedWord": "i",
      "case": "success",
      "end": 3.1799999999999997,
      "endOffset": 22,
      "phones": [
        {
          "duration": 0.28,
          "phone": "ay_S"
        }
      ],
      "start": 2.9,
      "startOffset": 21,
      "word": "I"
    },
    {
      "alignedWord": "read",
      "case": "success",
      "end": 3.3800000000000003,
      "endOffset": 27,
      "phones": [
        {
          "duration": 0.08,
          "phone": "r_B"
        },
        {
          "duration": 0.07,
          "phone": "eh_I"
        },
        {
          "duration": 0.05,
          "phone": "d_E"
        }
      ],
      "start": 3.18,
      "startOffset": 23,
      "word": "read"
    },
    {
      "alignedWord": "in",
      "case": "success",
      "end": 3.53,
      "endOffset": 30,
      "phones": [
        {
          "duration": 0.07,
          "phone": "ih_B"
        },
        {
          "duration": 0.08,
          "phone": "n_E"
        }
      ],
      "start": 3.38,
      "startOffset": 28,
      "word": "in"
    },
    {
      "alignedWord": "a",
      "case": "success",
      "end": 3.57,
      "endOffset": 32,
      "phones": [
        {
          "duration": 0.04,
          "phone": "ah_S"
        }
      ],
      "start": 3.53,
      "startOffset": 31,
      "word": "a"
    },
    {
      "alignedWord": "book",
      "case": "success",
      "end": 3.9,
      "endOffset": 37,
      "phones": [
        {
          "duration": 0.11,
          "phone": "b_B"
        },
        {
          "duration": 0.1,
          "phone": "uh_I"
        },
        {
          "duration": 0.12,
          "phone": "k_E"
        }
      ],
      "start": 3.57,
      "startOffset": 33,
      "word": "book"
    },
    {
      "alignedWord": "that",
      "case": "success",
      "end": 4.31,
      "endOffset": 42,
      "phones": [
        {
          "duration": 0.08,
          "phone": "dh_B"
        },
        {
          "duration": 0.08,
          "phone": "ah_I"
        },
        {
          "duration": 0.23,
          "phone": "t_E"
        }
      ],
      "start": 3.92,
      "startOffset": 38,
      "word": "that"
    },
    {
      "alignedWord": "giraffes",
      "case": "success",
      "end": 6.15,
      "endOffset": 52,
      "phones": [
        {
          "duration": 0.15,
          "phone": "jh_B"
        },
        {
          "duration": 0.15,
          "phone": "er_I"
        },
        {
          "duration": 0.16,
          "phone": "ae_I"
        },
        {
          "duration": 0.12,
          "phone": "f_I"
        },
        {
          "duration": 0.33,
          "phone": "s_E"
        }
      ],
      "start": 5.24,
      "startOffset": 44,
      "word": "giraffes"
    },
    {
      "alignedWord": "have",
      "case": "success",
      "end": 6.61,
      "endOffset": 58,
      "phones": [
        {
          "duration": 0.08,
          "phone": "hh_B"
        },
        {
          "duration": 0.06,
          "phone": "ae_I"
        },
        {
          "duration": 0.09,
          "phone": "v_E"
        }
      ],
      "start": 6.38,
      "startOffset": 54,
      "word": "have"
    },
    {
      "alignedWord": "no",
      "case": "success",
      "end": 6.8100000000000005,
      "endOffset": 61,
      "phones": [
        {
          "duration": 0.07,
          "phone": "n_B"
        },
        {
          "duration": 0.13,
          "phone": "ow_E"
        }
      ],
      "start": 6.61,
      "startOffset": 59,
      "word": "no"
    },
    {
      "alignedWord": "voices",
      "case": "success",
      "end": 7.539999999999999,
      "endOffset": 68,
      "phones": [
        {
          "duration": 0.13,
          "phone": "v_B"
        },
        {
          "duration": 0.14,
          "phone": "oy_I"
        },
        {
          "duration": 0.11,
          "phone": "s_I"
        },
        {
          "duration": 0.12,
          "phone": "ih_I"
        },
        {
          "duration": 0.23,
          "phone": "z_E"
        }
      ],
      "start": 6.81,
      "startOffset": 62,
      "word": "voices"
    },
    {
      "alignedWord": "the",
      "case": "success",
      "end": 8.88,
      "endOffset": 73,
      "phones": [
        {
          "duration": 0.08,
          "phone": "dh_B"
        },
        {
          "duration": 0.08,
          "phone": "ah_E"
        }
      ],
      "start": 8.72,
      "startOffset": 70,
      "word": "The"
    },
    {
      "alignedWord": "red",
      "case": "success",
      "end": 9.17,
      "endOffset": 77,
      "phones": [
        {
          "duration": 0.1,
          "phone": "r_B"
        },
        {
          "duration": 0.08,
          "phone": "eh_I"
        },
        {
          "duration": 0.11,
          "phone": "d_E"
        }
      ],
      "start": 8.88,
      "startOffset": 74,
      "word": "Red"
    },
    {
      "alignedWord": "sea",
      "case": "success",
      "end": 9.79,
      "endOffset": 81,
      "phones": [
        {
          "duration": 0.18,
          "phone": "s_B"
        },
        {
          "duration": 0.44,
          "phone": "iy_E"
        }
      ],
      "start": 9.17,
      "startOffset": 78,
      "word": "Sea"
    },
    {
      "alignedWord": "is",
      "case": "success",
      "end": 10.43,
      "endOffset": 85,
      "phones": [
        {
          "duration": 0.14,
          "phone": "ih_B"
        },
        {
          "duration": 0.1,
          "phone": "z_E"
        }
      ],
      "start": 10.19,
      "startOffset": 83,
      "word": "is"
    },
    {
      "alignedWord": "blue",
      "case": "success",
      "end": 10.959999,
      "endOffset": 90,
      "phones": [
        {
          "duration": 0.08,
          "phone": "b_B"
        },
        {
          "duration": 0.12,
          "phone": "l_I"
        },
        {
          "duration": 0.33,
          "phone": "uw_E"
        }
      ],
      "start": 10.429999,
      "startOffset": 86,
      "word": "blue"
    },
    {
      "alignedWord": "gorillas",
      "case": "success",
      "end": 12.88,
      "endOffset": 100,
      "phones": [
        {
          "duration": 0.11,
          "phone": "g_B"
        },
        {
          "duration": 0.18,
          "phone": "er_I"
        },
        {
          "duration": 0.09,
          "phone": "ih_I"
        },
        {
          "duration": 0.08,
          "phone": "l_I"
        },
        {
          "duration": 0.12,
          "phone": "ah_I"
        },
        {
          "duration": 0.32,
          "phone": "z_E"
        }
      ],
      "start": 11.98,
      "startOffset": 92,
      "word": "Gorillas"
    },
    {
      "alignedWord": "can't",
      "case": "success",
      "end": 13.92,
      "endOffset": 107,
      "phones": [
        {
          "duration": 0.06,
          "phone": "k_B"
        },
        {
          "duration": 0.17,
          "phone": "ae_I"
        },
        {
          "duration": 0.03,
          "phone": "n_I"
        },
        {
          "duration": 0.08,
          "phone": "t_E"
        }
      ],
      "start": 13.58,
      "startOffset": 102,
      "word": "can't"
    },
    {
      "alignedWord": "swim",
      "case": "success",
      "end": 14.46,
      "endOffset": 112,
      "phones": [
        {
          "duration": 0.13,
          "phone": "s_B"
        },
        {
          "duration": 0.07,
          "phone": "w_I"
        },
        {
          "duration": 0.12,
          "phone": "ih_I"
        },
        {
          "duration": 0.22,
          "phone": "m_E"
        }
      ],
      "start": 13.92,
      "startOffset": 108,
      "word": "swim"
    },
    {
      "alignedWord": "black",
      "case": "success",
      "end": 15.520000000000001,
      "endOffset": 119,
      "phones": [
        {
          "duration": 0.08,
          "phone": "b_B"
        },
        {
          "duration": 0.05,
          "phone": "l_I"
        },
        {
          "duration": 0.08,
          "phone": "ae_I"
        },
        {
          "duration": 0.1,
          "phone": "k_E"
        }
      ],
      "start": 15.21,
      "startOffset": 114,
      "word": "Black"
    },
    {
      "alignedWord": "<unk>",
      "case": "success",
      "end": 16.31,
      "endOffset": 127,
      "phones": [
        {
          "duration": 0.77,
          "phone": "oov_S"
        }
      ],
      "start": 15.54,
      "startOffset": 120,
      "word": "treacle"
    },
    {
      "alignedWord": "is",
      "case": "success",
      "end": 17.16,
      "endOffset": 131,
      "phones": [
        {
          "duration": 0.14,
          "phone": "ih_B"
        },
        {
          "duration": 0.09,
          "phone": "z_E"
        }
      ],
      "start": 16.93,
      "startOffset": 129,
      "word": "is"
    },
    {
      "alignedWord": "brown",
      "case": "success",
      "end": 17.81,
      "endOffset": 137,
      "phones": [
        {
          "duration": 0.09,
          "phone": "b_B"
        },
        {
          "duration": 0.1,
          "phone": "r_I"
        },
        {
          "duration": 0.23,
          "phone": "aw_I"
        },
        {
          "duration": 0.23,
          "phone": "n_E"
        }
      ],
      "start": 17.16,
      "startOffset": 132,
      "word": "brown"
    },
    {
      "alignedWord": "elephants",
      "case": "success",
      "end": 19.33,
      "endOffset": 148,
      "phones": [
        {
          "duration": 0.07,
          "phone": "eh_B"
        },
        {
          "duration": 0.06,
          "phone": "l_I"
        },
        {
          "duration": 0.05,
          "phone": "ah_I"
        },
        {
          "duration": 0.1,
          "phone": "f_I"
        },
        {
          "duration": 0.1,
          "phone": "ah_I"
        },
        {
          "duration": 0.09,
          "phone": "n_I"
        },
        {
          "duration": 0.07,
          "phone": "t_I"
        },
        {
          "duration": 0.29,
          "phone": "s_E"
        }
      ],
      "start": 18.5,
      "startOffset": 139,
      "word": "Elephants"
    },
    {
      "alignedWord": "can't",
      "case": "success",
      "end": 20.23,
      "endOffset": 155,
      "phones": [
        {
          "duration": 0.08,
          "phone": "k_B"
        },
        {
          "duration": 0.16,
          "phone": "ae_I"
        },
        {
          "duration": 0.03,
          "phone": "n_I"
        },
        {
          "duration": 0.07,
          "phone": "t_E"
        }
      ],
      "start": 19.89,
      "startOffset": 150,
      "word": "can't"
    },
    {
      "alignedWord": "jump",
      "case": "success",
      "end": 20.82,
      "endOffset": 160,
      "phones": [
        {
          "duration": 0.09,
          "phone": "jh_B"
        },
        {
          "duration": 0.17,
          "phone": "ah_I"
        },
        {
          "duration": 0.01,
          "phone": "m_I"
        },
        {
          "duration": 0.26,
          "phone": "p_E"
        }
      ],
      "start": 20.29,
      "startOffset": 156,
      "word": "jump"
    },
    {
      "alignedWord": "and",
      "case": "success",
      "end": 22.06,
      "endOffset": 165,
      "phones": [
        {
          "duration": 0.1,
          "phone": "ae_B"
        },
        {
          "duration": 0.05,
          "phone": "n_I"
        },
        {
          "duration": 0.07,
          "phone": "d_E"
        }
      ],
      "start": 21.84,
      "startOffset": 162,
      "word": "And"
    },
    {
      "alignedWord": "nothing",
      "case": "success",
      "end": 22.82,
      "endOffset": 173,
      "phones": [
        {
          "duration": 0.1,
          "phone": "n_B"
        },
        {
          "duration": 0.14,
          "phone": "ah_I"
        },
        {
          "duration": 0.15,
          "phone": "th_I"
        },
        {
          "duration": 0.12,
          "phone": "ih_I"
        },
        {
          "duration": 0.25,
          "phone": "ng_E"
        }
      ],
      "start": 22.06,
      "startOffset": 166,
      "word": "nothing"
    },
    {
      "alignedWord": "rhymes",
      "case": "success",
      "end": 24.14,
      "endOffset": 181,
      "phones": [
        {
          "duration": 0.16,
          "phone": "r_B"
        },
        {
          "duration": 0.11,
          "phone": "ay_I"
        },
        {
          "duration": 0.07,
          "phone": "m_I"
        },
        {
          "duration": 0.08,
          "phone": "z_E"
        }
      ],
      "start": 23.72,
      "startOffset": 175,
      "word": "rhymes"
    },
    {
      "alignedWord": "with",
      "case": "success",
      "end": 24.32,
      "endOffset": 186,
      "phones": [
        {
          "duration": 0.04,
          "phone": "w_B"
        },
        {
          "duration": 0.06,
          "phone": "ih_I"
        },
        {
          "duration": 0.08,
          "phone": "th_E"
        }
      ],
      "start": 24.14,
      "startOffset": 182,
      "word": "with"
    },
    {
      "alignedWord": "orange",
      "case": "success",
      "end": 24.97,
      "endOffset": 193,
      "phones": [
        {
          "duration": 0.11,
          "phone": "ao_B"
        },
        {
          "duration": 0.09,
          "phone": "r_I"
        },
        {
          "duration": 0.11,
          "phone": "ih_I"
        },
        {
          "duration": 0.11,
          "phone": "n_I"
        },
        {
          "duration": 0.23,
          "phone": "jh_E"
        }
      ],
      "start": 24.32,
      "startOffset": 187,
      "word": "orange"
    },
    {
      "alignedWord": "does",
      "case": "success",
      "end": 26.799999,
      "endOffset": 199,
      "phones": [
        {
          "duration": 0.08,
          "phone": "d_B"
        },
        {
          "duration": 0.07,
          "phone": "ah_I"
        },
        {
          "duration": 0.05,
          "phone": "z_E"
        }
      ],
      "start": 26.599999,
      "startOffset": 195,
      "word": "Does"
    },
    {
      "alignedWord": "it",
      "case": "success",
      "end": 27.0,
      "endOffset": 202,
      "phones": [
        {
          "duration": 0.09,
          "phone": "ih_B"
        },
        {
          "duration": 0.11,
          "phone": "t_E"
        }
      ],
      "start": 26.8,
      "startOffset": 200,
      "word": "it"
    }
  ]
}